textual_asciinema/__init__.py
textual_asciinema/__main__.py
textual_asciinema/controls.py
textual_asciinema/engine.py
textual_asciinema/parser.py
textual_asciinema/player.py
textual_asciinema/video_file.py
textual_asciinema-0.0.3.dist-info/entry_points.txt
textual_asciinema-0.0.3.dist-info/licenses/LICENSE.md
textual_asciinema-0.0.3.dist-info/WHEEL
textual_asciinema-0.0.3.dist-info/METADATA
textual_asciinema-0.0.3.dist-info/RECORD
