Metadata-Version: 2.4
Name: textual-asciinema
Version: 0.0.3
Summary: asciinema widget for textual
Author-email: Gareth Davidson <gaz@bitplane.net>
Requires-Python: >=3.10
License-File: LICENSE.md
Requires-Dist: textual
Requires-Dist: textual-tty
Requires-Dist: platformdirs
Requires-Dist: pre-commit ; extra == "dev"
Requires-Dist: pytest ; extra == "dev"
Requires-Dist: pytest-asyncio ; extra == "dev"
Requires-Dist: coverage ; extra == "dev"
Requires-Dist: pytest-cov ; extra == "dev"
Requires-Dist: build ; extra == "dev"
Requires-Dist: twine ; extra == "dev"
Requires-Dist: ruff ; extra == "dev"
Requires-Dist: pydoc-markdown ; extra == "dev"
Requires-Dist: mkdocs ; extra == "dev"
Requires-Dist: mkdocs-material ; extra == "dev"
Provides-Extra: dev
